tests/__init__.py
tests/conftest.py
tests/test_default.py
tests/test_group.py
tests/test_shm_size.py
tests/test_validator.py
worker_configuration/__init__.py
worker_configuration/cli.py
worker_configuration/convert.py
worker_configuration/rules.py
worker_configuration/schema.py
worker_configuration/schema.yml
worker_configuration/validator.py
teklia_worker_configuration-0.2.2.dist-info/METADATA
teklia_worker_configuration-0.2.2.dist-info/WHEEL
teklia_worker_configuration-0.2.2.dist-info/entry_points.txt
teklia_worker_configuration-0.2.2.dist-info/top_level.txt
teklia_worker_configuration-0.2.2.dist-info/RECORD
