Metadata-Version: 2.4
Name: teklia-worker-configuration
Version: 0.2.2
Summary: Scripts for Arkindex worker configuration
Author-email: Teklia <contact@teklia.com>
Maintainer-email: Teklia <contact@teklia.com>
Keywords: python
Classifier: Programming Language :: Python :: 3 :: Only
Classifier: Programming Language :: Python :: 3.10
Classifier: Programming Language :: Python :: 3.11
Requires-Python: >=3.10
Requires-Dist: yamale==6.0.0
